poetry_plugin_i/__init__.py
poetry_plugin_i/i_plugin.py
poetry_plugin_i-0.1.0.dist-info/LICENSE
poetry_plugin_i-0.1.0.dist-info/METADATA
poetry_plugin_i-0.1.0.dist-info/WHEEL
poetry_plugin_i-0.1.0.dist-info/entry_points.txt
poetry_plugin_i-0.1.0.dist-info/RECORD
